zfex-1.6.0.1.dist-info/COPYING.TGPPL.rst
zfex-1.6.0.1.dist-info/COPYING.GPL
zfex-1.6.0.1.dist-info/entry_points.txt
zfex-1.6.0.1.dist-info/METADATA
zfex-1.6.0.1.dist-info/top_level.txt
zfex-1.6.0.1.dist-info/RECORD
zfex-1.6.0.1.dist-info/WHEEL
zfex/_zfex_test.pypy37-pp73-x86_64-linux-gnu.so
zfex/__init__.py
zfex/_zfex.pyx
zfex/zfex_macros.h
zfex/_zfex_test.pyx
zfex/zfex_pp.h
zfex/_zfex_status.pxi
zfex/cmdline_zunfex.py
zfex/zfex_status.h
zfex/_zfex_test.c
zfex/zfex_bytemask.h
zfex/zfex.c
zfex/easyfec.py
zfex/_zfex.pypy37-pp73-x86_64-linux-gnu.so
zfex/filefec.py
zfex/zfex.h
zfex/_version.py
zfex/.gitignore
zfex/_zfex.c
zfex/cmdline_zfex.py
zfex/distutils/README.rst
zfex/distutils/__init__.py
zfex/distutils/LICENSE.ccompilercapabilities_py
zfex/distutils/ccompilercapabilities.py
zfex/distutils/__pycache__/__init__.cpython-39.pyc
zfex/distutils/__pycache__/ccompilercapabilities.cpython-39.pyc
zfex/distutils/__pycache__/__init__.cpython-36.pyc
zfex/distutils/__pycache__/ccompilercapabilities.cpython-37.pyc
zfex/distutils/__pycache__/__init__.pypy37.pyc
zfex/distutils/__pycache__/__init__.cpython-38.pyc
zfex/distutils/__pycache__/ccompilercapabilities.pypy37.pyc
zfex/distutils/__pycache__/ccompilercapabilities.cpython-38.pyc
zfex/distutils/__pycache__/__init__.cpython-310.pyc
zfex/distutils/__pycache__/ccompilercapabilities.cpython-36.pyc
zfex/distutils/__pycache__/ccompilercapabilities.cpython-311.pyc
zfex/distutils/__pycache__/__init__.cpython-37.pyc
zfex/distutils/__pycache__/__init__.cpython-311.pyc
zfex/distutils/__pycache__/ccompilercapabilities.cpython-310.pyc
zfex/__pycache__/__init__.cpython-39.pyc
zfex/__pycache__/__init__.cpython-36.pyc
zfex/__pycache__/_version.cpython-37.pyc
zfex/__pycache__/_version.cpython-310.pyc
zfex/__pycache__/_version.pypy37.pyc
zfex/__pycache__/_version.cpython-36.pyc
zfex/__pycache__/__init__.pypy37.pyc
zfex/__pycache__/_version.cpython-39.pyc
zfex/__pycache__/_version.cpython-38.pyc
zfex/__pycache__/_version.cpython-311.pyc
zfex/__pycache__/__init__.cpython-38.pyc
zfex/__pycache__/__init__.cpython-310.pyc
zfex/__pycache__/__init__.cpython-37.pyc
zfex/__pycache__/__init__.cpython-311.pyc
zfex/test/__init__.py
