Metadata-Version: 2.1
Name: zfex
Version: 1.6.0.1
Summary: A fast, efficient, portable erasure coding tool
Home-page: https://github.com/WojciechMigda/zfex
Author: Wojciech Migda
Author-email: wojtek.golf@interia.pl
License: GPL-2+
Platform: UNKNOWN
Classifier: Development Status :: 5 - Production/Stable
Classifier: Environment :: Console
Classifier: License :: OSI Approved
Classifier: License :: OSI Approved :: GNU General Public License v2 or later (GPLv2+)
Classifier: License :: DFSG approved
Classifier: License :: Other/Proprietary License
Classifier: Intended Audience :: Developers
Classifier: Intended Audience :: End Users/Desktop
Classifier: Intended Audience :: System Administrators
Classifier: Operating System :: Microsoft
Classifier: Operating System :: Microsoft :: Windows
Classifier: Operating System :: Unix
Classifier: Operating System :: POSIX :: Linux
Classifier: Operating System :: POSIX
Classifier: Operating System :: MacOS :: MacOS X
Classifier: Operating System :: Microsoft :: Windows :: Windows NT/2000
Classifier: Operating System :: OS Independent
Classifier: Natural Language :: English
Classifier: Programming Language :: C
Classifier: Programming Language :: Python
Classifier: Programming Language :: Python :: 3
Classifier: Programming Language :: Python :: 3.7
Classifier: Programming Language :: Python :: 3.8
Classifier: Topic :: Utilities
Classifier: Topic :: System :: Systems Administration
Classifier: Topic :: System :: Filesystems
Classifier: Topic :: System :: Distributed Computing
Classifier: Topic :: Software Development :: Libraries
Classifier: Topic :: Communications :: Usenet News
Classifier: Topic :: System :: Archiving :: Backup
Classifier: Topic :: System :: Archiving :: Mirroring
Classifier: Topic :: System :: Archiving
License-File: COPYING.GPL
License-File: COPYING.TGPPL.rst
Provides-Extra: bench
Requires-Dist: pyutil (>=3.0.0) ; extra == 'bench'
Provides-Extra: test
Requires-Dist: twisted ; extra == 'test'
Requires-Dist: pyutil (>=3.0.0) ; extra == 'test'
